alphaml/__init__.py
alphaml/guip.py
alphaml/guir.py
alphaml/pred.py
alphaml/run.py
alphaml/models/__init__.py
alphaml/models/abc.py
alphaml/models/all.py
alphaml/models/cbc.py
alphaml/models/etc.py
alphaml/models/gbc.py
alphaml/models/hgb.py
alphaml/models/lgb.py
alphaml/models/mlp.py
alphaml/models/rfc.py
alphaml/models/sen.py
alphaml/models/sl1.py
alphaml/models/sl2.py
alphaml/models/svc.py
alphaml/models/svn.py
alphaml/models/tab.py
alphaml/models/xgb.py
alphaml/utils/__init__.py
alphaml/utils/all_ml.py
alphaml/utils/deeplink.py
alphaml/utils/metrics.py
alphaml/utils/prep.py
alphaml/utils/run_model.py
alphaml/utils/utils.py
alphaml/utils/binary_tabnet/__init__.py
alphaml/utils/binary_tabnet/abstract_model.py
alphaml/utils/binary_tabnet/callbacks.py
alphaml/utils/binary_tabnet/metrics.py
alphaml/utils/binary_tabnet/multiclass_utils.py
alphaml/utils/binary_tabnet/pretraining.py
alphaml/utils/binary_tabnet/pretraining_utils.py
alphaml/utils/binary_tabnet/sparsemax.py
alphaml/utils/binary_tabnet/tab_model.py
alphaml/utils/binary_tabnet/tab_network.py
alphaml/utils/binary_tabnet/utils.py
alphaml-0.1.3.dist-info/LICENSE
alphaml-0.1.3.dist-info/METADATA
alphaml-0.1.3.dist-info/WHEEL
alphaml-0.1.3.dist-info/top_level.txt
alphaml-0.1.3.dist-info/RECORD
