Metadata-Version: 2.1
Name: alphaml
Version: 0.1.3
Summary: Build a CLETE Binary Classification Model
Home-page: https://www.kazilab.se
Author: Julhash Kazi
Author-email: aml@kazilab.se
License: Apache-2.0
Platform: any
License-File: LICENSE
Requires-Dist: catboost
Requires-Dist: imbalanced-learn
Requires-Dist: IPython
Requires-Dist: kaleido
Requires-Dist: lime
Requires-Dist: lightgbm
Requires-Dist: matplotlib
Requires-Dist: numpy
Requires-Dist: openpyxl
Requires-Dist: optuna
Requires-Dist: pandas
Requires-Dist: plotly
Requires-Dist: requests
Requires-Dist: scipy
Requires-Dist: scikit-learn
Requires-Dist: scikit-optimize
Requires-Dist: shap
Requires-Dist: tensorflow
Requires-Dist: torch
Requires-Dist: tqdm
Requires-Dist: xgboost
